bmdf/__init__.py
bmdf/utils.py
bmdf/cli/__init__.py
mdcmd/__init__.py
mdcmd/cli/__init__.py
mdcmd-0.7.4.dist-info/licenses/LICENSE
toc/__init__.py
toc/mktoc.py
mdcmd-0.7.4.dist-info/METADATA
mdcmd-0.7.4.dist-info/WHEEL
mdcmd-0.7.4.dist-info/entry_points.txt
mdcmd-0.7.4.dist-info/top_level.txt
mdcmd-0.7.4.dist-info/RECORD
