Metadata-Version: 2.4
Name: mdcmd
Version: 0.7.4
Summary: Execute commands in Markdown files, embed output, generate TOCs
Author-email: Ryan Williams <ryan@runsascoded.com>
License: MIT
Project-URL: Homepage, https://github.com/runsascoded/mdcmd
Project-URL: Repository, https://github.com/runsascoded/mdcmd.git
Project-URL: Bug Tracker, https://github.com/runsascoded/mdcmd/issues
Requires-Python: >=3.10
License-File: LICENSE
Requires-Dist: utz>=0.21.4
Requires-Dist: click>=8
Provides-Extra: test
Requires-Dist: pytest; extra == "test"
Dynamic: license-file
